dagster_meltano/__init__.py
dagster_meltano/exceptions.py
dagster_meltano/generation.py
dagster_meltano/job.py
dagster_meltano/logging.yaml
dagster_meltano/meltano_resource.py
dagster_meltano/ops.py
dagster_meltano/schedule.py
dagster_meltano/utils.py
dagster_meltano-1.5.5.dist-info/LICENSE
dagster_meltano-1.5.5.dist-info/METADATA
dagster_meltano-1.5.5.dist-info/WHEEL
dagster_meltano-1.5.5.dist-info/RECORD
