Metadata-Version: 2.1
Name: dagster-meltano
Version: 1.5.5
Summary: A dagster plugin that allows you to run your Meltano project inside Dagster.
License: Apache 2.0
Author: Quantile Development
Requires-Python: >=3.8,<3.13
Classifier: License :: Other/Proprietary License
Classifier: Programming Language :: Python :: 3
Classifier: Programming Language :: Python :: 3.8
Classifier: Programming Language :: Python :: 3.9
Classifier: Programming Language :: Python :: 3.10
Classifier: Programming Language :: Python :: 3.11
Classifier: Programming Language :: Python :: 3.12
Requires-Dist: dagster (>=1.3,<2)
Requires-Dist: dagster-shell (>=0,<1)
